hello_niksingh710.py
hello_niksingh710-0.0.2.dist-info/LICENSE.txt
hello_niksingh710-0.0.2.dist-info/METADATA
hello_niksingh710-0.0.2.dist-info/WHEEL
hello_niksingh710-0.0.2.dist-info/top_level.txt
hello_niksingh710-0.0.2.dist-info/RECORD
