Metadata-Version: 2.1
Name: hello-niksingh710
Version: 0.0.2
Summary: Says Hello!
Home-page: https://github.com/niksingh710/hello_niksingh710
Author: Nikhil Singh
Author-email: nik.singh710@gmail.com
License: UNKNOWN
Platform: UNKNOWN
Classifier: Programming Language :: Python :: 3.6
Classifier: Programming Language :: Python :: 3.7
Classifier: Programming Language :: Python :: 3.8
Classifier: Programming Language :: Python :: 3.9
Classifier: Programming Language :: Python :: 3.10
Classifier: License :: OSI Approved :: GNU General Public License v3 (GPLv3)
Classifier: Operating System :: OS Independent
